please/__init__.py
please/please.py
please/quotes.json
please_cli-0.3.1.dist-info/entry_points.txt
please_cli-0.3.1.dist-info/WHEEL
please_cli-0.3.1.dist-info/METADATA
please_cli-0.3.1.dist-info/LICENSE.md
please_cli-0.3.1.dist-info/RECORD
