Metadata-Version: 2.1
Name: please-cli
Version: 0.3.1
Summary: A new tab page for your terminal
Home-page: https://github.com/NayamAmarshe/please
License: MIT
Keywords: please,cli,new tab
Author: Nayam Amarshe
Requires-Python: >=3.8,<4.0
Classifier: License :: OSI Approved :: MIT License
Classifier: Programming Language :: Python :: 3
Classifier: Programming Language :: Python :: 3.8
Classifier: Programming Language :: Python :: 3.9
Classifier: Programming Language :: Python :: 3.10
Classifier: Programming Language :: Python :: 3.11
Requires-Dist: rich (>=12.3.0,<13.0.0)
Requires-Dist: typer (>=0.4.1,<0.5.0)
Project-URL: Documentation, https://github.com/NayamAmarshe/please
Project-URL: Repository, https://github.com/NayamAmarshe/please
